apilib/__init__.py
apilib/auth.py
apilib/commands.py
apilib/core.py
apilib/crypto.py
apilib/password_commands.py
apilib/storage.py
volti-1.1.0.dist-info/licenses/LICENSE
volti-1.1.0.dist-info/METADATA
volti-1.1.0.dist-info/WHEEL
volti-1.1.0.dist-info/entry_points.txt
volti-1.1.0.dist-info/top_level.txt
volti-1.1.0.dist-info/RECORD
