Metadata-Version: 2.4
Name: volti
Version: 1.1.0
Summary: 🔐 Secure API Key Manager - Minimal CLI tool and Python library for managing API keys with military-grade encryption, password authentication, and cross-platform support. Store, retrieve, and organize your API keys safely with intuitive commands and bulk .env import capabilities.
Author-email: Lokesh <lokeshpantangi@gmail.com>, Aditya <aditya268244@gmail.com>
Project-URL: Homepage, https://github.com/lokeshpantangi/volti
Project-URL: Repository, https://github.com/lokeshpantangi/volti.git
Project-URL: Issues, https://github.com/lokeshpantangi/volti/issues
Project-URL: Documentation, https://github.com/lokeshpantangi/volti#readme
Project-URL: Changelog, https://github.com/lokeshpantangi/volti/releases
Project-URL: Bug Reports, https://github.com/lokeshpantangi/volti/issues
Project-URL: Source Code, https://github.com/lokeshpantangi/volti
Keywords: api-keys,security,encryption,cli,credentials,password-manager,developer-tools
Classifier: Development Status :: 5 - Production/Stable
Classifier: Intended Audience :: Developers
Classifier: Intended Audience :: System Administrators
Classifier: License :: OSI Approved :: MIT License
Classifier: Programming Language :: Python :: 3
Classifier: Programming Language :: Python :: 3.6
Classifier: Programming Language :: Python :: 3.7
Classifier: Programming Language :: Python :: 3.8
Classifier: Programming Language :: Python :: 3.9
Classifier: Programming Language :: Python :: 3.10
Classifier: Programming Language :: Python :: 3.11
Classifier: Programming Language :: Python :: 3.12
Classifier: Programming Language :: Python :: 3.13
Classifier: Topic :: Security :: Cryptography
Classifier: Topic :: Software Development :: Libraries :: Python Modules
Classifier: Topic :: System :: Systems Administration
Classifier: Topic :: Utilities
Classifier: Environment :: Console
Classifier: Operating System :: OS Independent
Requires-Python: >=3.6
License-File: LICENSE
Requires-Dist: cryptography>=3.4.8
Requires-Dist: click>=8.0.0
Requires-Dist: pywin32; platform_system == "Windows"
Requires-Dist: argon2-cffi
Requires-Dist: pyperclip
Dynamic: license-file
